aliyunsdkehpc/__init__.py
aliyunsdkehpc/endpoint.py
aliyunsdkehpc/request/__init__.py
aliyunsdkehpc/request/v20180412/AddContainerAppRequest.py
aliyunsdkehpc/request/v20180412/AddExistedNodesRequest.py
aliyunsdkehpc/request/v20180412/AddLocalNodesRequest.py
aliyunsdkehpc/request/v20180412/AddNodesRequest.py
aliyunsdkehpc/request/v20180412/AddQueueRequest.py
aliyunsdkehpc/request/v20180412/AddSecurityGroupRequest.py
aliyunsdkehpc/request/v20180412/AddUsersRequest.py
aliyunsdkehpc/request/v20180412/ApplyNodesRequest.py
aliyunsdkehpc/request/v20180412/CreateClusterRequest.py
aliyunsdkehpc/request/v20180412/CreateGWSClusterRequest.py
aliyunsdkehpc/request/v20180412/CreateGWSImageRequest.py
aliyunsdkehpc/request/v20180412/CreateGWSInstanceRequest.py
aliyunsdkehpc/request/v20180412/CreateHybridClusterRequest.py
aliyunsdkehpc/request/v20180412/CreateJobFileRequest.py
aliyunsdkehpc/request/v20180412/CreateJobTemplateRequest.py
aliyunsdkehpc/request/v20180412/DeleteClusterRequest.py
aliyunsdkehpc/request/v20180412/DeleteContainerAppsRequest.py
aliyunsdkehpc/request/v20180412/DeleteGWSClusterRequest.py
aliyunsdkehpc/request/v20180412/DeleteGWSInstanceRequest.py
aliyunsdkehpc/request/v20180412/DeleteImageRequest.py
aliyunsdkehpc/request/v20180412/DeleteJobTemplatesRequest.py
aliyunsdkehpc/request/v20180412/DeleteJobsRequest.py
aliyunsdkehpc/request/v20180412/DeleteLocalImageRequest.py
aliyunsdkehpc/request/v20180412/DeleteNodesRequest.py
aliyunsdkehpc/request/v20180412/DeleteQueueRequest.py
aliyunsdkehpc/request/v20180412/DeleteSecurityGroupRequest.py
aliyunsdkehpc/request/v20180412/DeleteUsersRequest.py
aliyunsdkehpc/request/v20180412/DescribeAutoScaleConfigRequest.py
aliyunsdkehpc/request/v20180412/DescribeClusterRequest.py
aliyunsdkehpc/request/v20180412/DescribeContainerAppRequest.py
aliyunsdkehpc/request/v20180412/DescribeEstackImageRequest.py
aliyunsdkehpc/request/v20180412/DescribeGWSClusterPolicyRequest.py
aliyunsdkehpc/request/v20180412/DescribeGWSClustersRequest.py
aliyun_python_sdk_ehpc-1.14.21.dist-info/LICENSE
aliyun_python_sdk_ehpc-1.14.21.dist-info/METADATA
aliyun_python_sdk_ehpc-1.14.21.dist-info/WHEEL
aliyun_python_sdk_ehpc-1.14.21.dist-info/top_level.txt
aliyun_python_sdk_ehpc-1.14.21.dist-info/RECORD
